python_speech_features/__init__.py
python_speech_features/base.py
python_speech_features/base_orig.py
python_speech_features/sigproc.py
python_speech_features/sigproc_orig.py
paddlespeech_feat-0.1.0.dist-info/LICENSE
paddlespeech_feat-0.1.0.dist-info/METADATA
paddlespeech_feat-0.1.0.dist-info/WHEEL
paddlespeech_feat-0.1.0.dist-info/top_level.txt
paddlespeech_feat-0.1.0.dist-info/RECORD
